pureml/__init__.py
pureml/log.txt
pureml/cli/__init__.py
pureml/cli/auth.py
pureml/cli/helpers.py
pureml/cli/main.py
pureml/cli/orgs.py
pureml/cli/public.pem
pureml/cli/puremlconfig.py
pureml/cli/secrets.py
pureml/components/__init__.py
pureml/components/auth.py
pureml/components/dataset.py
pureml/components/model.py
pureml/components/log/__init__.py
pureml/components/log/arrays.py
pureml/components/log/artifacts.py
pureml/components/log/audio.py
pureml/components/log/figure.py
pureml/components/log/image.py
pureml/components/log/log.py
pureml/components/log/metrics.py
pureml/components/log/params.py
pureml/components/log/pip_requirement.py
pureml/components/log/predict.py
pureml/components/log/resources.py
pureml/components/log/tabular.py
pureml/components/log/video.py
pureml/config/__init__.py
pureml/config/parser.py
pureml/decorators/__init__.py
pureml/decorators/dataset.py
pureml/decorators/load_data.py
pureml/decorators/model.py
pureml/decorators/pip_requirements.py
pureml/decorators/predict.py
pureml/decorators/transformer.py
pureml/gateway/__init__.py
pureml/gateway/provider.py
pureml/gateway/providers/azure_openai.py
pureml/gateway/providers/openai_provider.py
pureml/lineage/__init__.py
pureml/lineage/data/__init__.py
pureml/lineage/data/create_lineage.py
pureml/package/__init__.py
pureml/package/docker.py
pureml/package/fastapi.py
pureml/package_test/cli/test_main.py
pureml/package_test/components/__init__.py
pureml/package_test/components/test_auth.py
pureml/package_test/components/test_dataset.py
pureml/packaging/__init__.py
pureml/packaging/errors.py
pureml/packaging/log.txt
pureml/packaging/model_framework.py
pureml/packaging/packaging.py
pureml/packaging/packaging_utils.py
pureml/packaging/model_packaging/__init__.py
pureml/packaging/model_packaging/catboost.py
pureml/packaging/model_packaging/custom.py
pureml/packaging/model_packaging/keras.py
pureml/packaging/model_packaging/lightgbm.py
pureml/packaging/model_packaging/pytorch.py
pureml-0.4.8.dist-info/METADATA
pureml-0.4.8.dist-info/WHEEL
pureml-0.4.8.dist-info/entry_points.txt
pureml-0.4.8.dist-info/RECORD
